manysim
