Metadata-Version: 1.0
Name: manysim
Version: 0.0-1
Summary: Perform Simulations on the Amazon Elastic Compute Cloud
Home-page: http://code.google.com/p/manysim/
Author: Christopher M Poole
Author-email: mail@christopherpoole.net
License: UNKNOWN
Platform: UNKNOWN
Classifier: Development Status :: 4 - Beta
Classifier: Environment :: Console
Classifier: Programming Language :: Python
Classifier: Topic :: Scientific/Engineering
Classifier: License :: OSI Approved :: Apache Software License
